cbibs/__init__.py
cbibs/buoy.py
python_cbibs-0.0.3.dist-info/LICENSE
python_cbibs-0.0.3.dist-info/METADATA
python_cbibs-0.0.3.dist-info/WHEEL
python_cbibs-0.0.3.dist-info/top_level.txt
python_cbibs-0.0.3.dist-info/RECORD
