Metadata-Version: 2.1
Name: python-cbibs
Version: 0.0.3
Summary: Python wrapper for interacting with the CBIBS API
Author-email: FLetcher Sims <fletcher.sims@gmail.com>
Project-URL: Homepage, https://github.com/fletchsims/python-cbibs
Project-URL: Issues, https://github.com/fletchsims/python-cbibs/issues
Classifier: Programming Language :: Python :: 3
Classifier: License :: OSI Approved :: MIT License
Classifier: Operating System :: OS Independent
Requires-Python: >=3.8
License-File: LICENSE
